Metadata-Version: 2.1
Name: projectpredict
Version: 0.0.1a2
Summary: A library to help schedule projects intelligently.
Home-page: https://github.com/JustinTervala/ProjectPredict
Author: Justin Tervala
Author-email: jgtervala@gmail.com
License: MIT
Download-URL: https://github.com/JustinTervala/ProjectPredict/archive/v0.0.1a2.tar.gz
Keywords: scheduling,project management
Platform: UNKNOWN
Classifier: Development Status :: 3 - Alpha
Classifier: Topic :: Office/Business :: Scheduling
Classifier: License :: OSI Approved :: MIT License
Classifier: Natural Language :: English
Classifier: Operating System :: OS Independent
